understory/media/__init__.py
understory/media/templates/__init__.py
understory/media/templates/index.html
understory/media/templates/media_added.html
understory/media/templates/media_deleted.html
understory_media-0.0.40.dist-info/entry_points.txt
understory_media-0.0.40.dist-info/LICENSE
understory_media-0.0.40.dist-info/WHEEL
understory_media-0.0.40.dist-info/METADATA
understory_media-0.0.40.dist-info/RECORD
